{"date":"วันพฤหัสบดีที่ 11 กรกฏาคม 2562","data":[{"league_name":"ยูฟ่า ยูโรปา ลีก (UEFA Europa League)","time":"03:00","home":"เซนต์ยาร์นาน","away":"เลวาเดีย ทาลลินน์","ratio":"0.5/1 -5","forecast":["2","2"],"result":["2","1"],"opinion":"เลวาเดีย ทาลลินด์ บุกมาเล่นแบบชิลล์ๆ ดึงเสมอ","winner":"เซนต์ยาร์นาน"},{"league_name":"ยูฟ่า ยูโรปา ลีก (UEFA Europa League)","time":"03:00","home":"เซนต์ยาร์นาน","away":"เลวาเดีย ทาลลินน์","ratio":"0.5/1 -5","forecast":["2","2"],"result":["2","1"],"opinion":"เลวาเดีย ทาลลินด์ บุกมาเล่นแบบชิลล์ๆ ดึงเสมอ","winner":"เซนต์ยาร์นาน"},{"league_name":"ยูฟ่า ยูโรปา ลีก (UEFA Europa League)","time":"03:00","home":"เซนต์ยาร์นาน","away":"เลวาเดีย ทาลลินน์","ratio":"0.5/1 -5","forecast":["2","2"],"result":["2","1"],"opinion":"เลวาเดีย ทาลลินด์ บุกมาเล่นแบบชิลล์ๆ ดึงเสมอ","winner":"เซนต์ยาร์นาน"},{"league_name":"ยูฟ่า ยูโรปา ลีก (UEFA Europa League)","time":"03:00","home":"เซนต์ยาร์นาน","away":"เลวาเดีย ทาลลินน์","ratio":"0.5/1 -5","forecast":["2","2"],"result":["2","1"],"opinion":"เลวาเดีย ทาลลินด์ บุกมาเล่นแบบชิลล์ๆ ดึงเสมอ","winner":"เซนต์ยาร์นาน"},{"league_name":"ยูฟ่า ยูโรปา ลีก (UEFA Europa League)","time":"03:00","home":"เซนต์ยาร์นาน","away":"เลวาเดีย ทาลลินน์","ratio":"0.5/1 -5","forecast":["2","2"],"result":["2","1"],"opinion":"เลวาเดีย ทาลลินด์ บุกมาเล่นแบบชิลล์ๆ ดึงเสมอ","winner":"เซนต์ยาร์นาน"},{"league_name":"ยูฟ่า ยูโรปา ลีก (UEFA Europa League)","time":"03:00","home":"เซนต์ยาร์นาน","away":"เลวาเดีย ทาลลินน์","ratio":"0.5/1 -5","forecast":["2","2"],"result":["2","1"],"opinion":"เลวาเดีย ทาลลินด์ บุกมาเล่นแบบชิลล์ๆ ดึงเสมอ","winner":"เซนต์ยาร์นาน"},{"league_name":"ยูฟ่า ยูโรปา ลีก (UEFA Europa League)","time":"03:00","home":"เซนต์ยาร์นาน","away":"เลวาเดีย ทาลลินน์","ratio":"0.5/1 -5","forecast":["2","2"],"result":["2","1"],"opinion":"เลวาเดีย ทาลลินด์ บุกมาเล่นแบบชิลล์ๆ ดึงเสมอ","winner":"เซนต์ยาร์นาน"},{"league_name":"ยูฟ่า ยูโรปา ลีก (UEFA Europa League)","time":"03:00","home":"เซนต์ยาร์นาน","away":"เลวาเดีย ทาลลินน์","ratio":"0.5/1 -5","forecast":["2","2"],"result":["2","1"],"opinion":"เลวาเดีย ทาลลินด์ บุกมาเล่นแบบชิลล์ๆ ดึงเสมอ","winner":"เซนต์ยาร์นาน"},{"league_name":"ยูฟ่า ยูโรปา ลีก (UEFA Europa League)","time":"03:00","home":"เซนต์ยาร์นาน","away":"เลวาเดีย ทาลลินน์","ratio":"0.5/1 -5","forecast":["2","2"],"result":["2","1"],"opinion":"เลวาเดีย ทาลลินด์ บุกมาเล่นแบบชิลล์ๆ ดึงเสมอ","winner":"เซนต์ยาร์นาน"},{"league_name":"ยูฟ่า ยูโรปา ลีก (UEFA Europa League)","time":"03:00","home":"เซนต์ยาร์นาน","away":"เลวาเดีย ทาลลินน์","ratio":"0.5/1 -5","forecast":["2","2"],"result":["2","1"],"opinion":"เลวาเดีย ทาลลินด์ บุกมาเล่นแบบชิลล์ๆ ดึงเสมอ","winner":"เซนต์ยาร์นาน"},{"league_name":"ยูฟ่า ยูโรปา ลีก (UEFA Europa League)","time":"03:00","home":"เซนต์ยาร์นาน","away":"เลวาเดีย ทาลลินน์","ratio":"0.5/1 -5","forecast":["2","2"],"result":["2","1"],"opinion":"เลวาเดีย ทาลลินด์ บุกมาเล่นแบบชิลล์ๆ ดึงเสมอ","winner":"เซนต์ยาร์นาน"},{"league_name":"ยูฟ่า ยูโรปา ลีก (UEFA Europa League)","time":"03:00","home":"เซนต์ยาร์นาน","away":"เลวาเดีย ทาลลินน์","ratio":"0.5/1 -5","forecast":["2","2"],"result":["2","1"],"opinion":"เลวาเดีย ทาลลินด์ บุกมาเล่นแบบชิลล์ๆ ดึงเสมอ","winner":"เซนต์ยาร์นาน"},{"league_name":"ยูฟ่า ยูโรปา ลีก (UEFA Europa League)","time":"03:00","home":"เซนต์ยาร์นาน","away":"เลวาเดีย ทาลลินน์","ratio":"0.5/1 -5","forecast":["2","2"],"result":["2","1"],"opinion":"เลวาเดีย ทาลลินด์ บุกมาเล่นแบบชิลล์ๆ ดึงเสมอ","winner":"เซนต์ยาร์นาน"},{"league_name":"ยูฟ่า ยูโรปา ลีก (UEFA Europa League)","time":"03:00","home":"เซนต์ยาร์นาน","away":"เลวาเดีย ทาลลินน์","ratio":"0.5/1 -5","forecast":["2","2"],"result":["2","1"],"opinion":"เลวาเดีย ทาลลินด์ บุกมาเล่นแบบชิลล์ๆ ดึงเสมอ","winner":"เซนต์ยาร์นาน"},{"league_name":"ยูฟ่า ยูโรปา ลีก (UEFA Europa League)","time":"03:00","home":"เซนต์ยาร์นาน","away":"เลวาเดีย ทาลลินน์","ratio":"0.5/1 -5","forecast":["2","2"],"result":["2","1"],"opinion":"เลวาเดีย ทาลลินด์ บุกมาเล่นแบบชิลล์ๆ ดึงเสมอ","winner":"เซนต์ยาร์นาน"},{"league_name":"ยูฟ่า ยูโรปา ลีก (UEFA Europa League)","time":"03:00","home":"เซนต์ยาร์นาน","away":"เลวาเดีย ทาลลินน์","ratio":"0.5/1 -5","forecast":["2","2"],"result":["2","1"],"opinion":"เลวาเดีย ทาลลินด์ บุกมาเล่นแบบชิลล์ๆ ดึงเสมอ","winner":"เซนต์ยาร์นาน"},{"league_name":"ยูฟ่า ยูโรปา ลีก (UEFA Europa League)","time":"03:00","home":"เซนต์ยาร์นาน","away":"เลวาเดีย ทาลลินน์","ratio":"0.5/1 -5","forecast":["2","2"],"result":["2","1"],"opinion":"เลวาเดีย ทาลลินด์ บุกมาเล่นแบบชิลล์ๆ ดึงเสมอ","winner":"เซนต์ยาร์นาน"},{"league_name":"ยูฟ่า ยูโรปา ลีก (UEFA Europa League)","time":"03:00","home":"เซนต์ยาร์นาน","away":"เลวาเดีย ทาลลินน์","ratio":"0.5/1 -5","forecast":["2","2"],"result":["2","1"],"opinion":"เลวาเดีย ทาลลินด์ บุกมาเล่นแบบชิลล์ๆ ดึงเสมอ","winner":"เซนต์ยาร์นาน"},{"league_name":"ยูฟ่า ยูโรปา ลีก (UEFA Europa League)","time":"03:00","home":"เซนต์ยาร์นาน","away":"เลวาเดีย ทาลลินน์","ratio":"0.5/1 -5","forecast":["2","2"],"result":["2","1"],"opinion":"เลวาเดีย ทาลลินด์ บุกมาเล่นแบบชิลล์ๆ ดึงเสมอ","winner":"เซนต์ยาร์นาน"},{"league_name":"ยูฟ่า ยูโรปา ลีก (UEFA Europa League)","time":"03:00","home":"เซนต์ยาร์นาน","away":"เลวาเดีย ทาลลินน์","ratio":"0.5/1 -5","forecast":["2","2"],"result":["2","1"],"opinion":"เลวาเดีย ทาลลินด์ บุกมาเล่นแบบชิลล์ๆ ดึงเสมอ","winner":"เซนต์ยาร์นาน"},{"league_name":"ยูฟ่า ยูโรปา ลีก (UEFA Europa League)","time":"03:00","home":"เซนต์ยาร์นาน","away":"เลวาเดีย ทาลลินน์","ratio":"0.5/1 -5","forecast":["2","2"],"result":["2","1"],"opinion":"เลวาเดีย ทาลลินด์ บุกมาเล่นแบบชิลล์ๆ ดึงเสมอ","winner":"เซนต์ยาร์นาน"},{"league_name":"ยูฟ่า ยูโรปา ลีก (UEFA Europa League)","time":"03:00","home":"เซนต์ยาร์นาน","away":"เลวาเดีย ทาลลินน์","ratio":"0.5/1 -5","forecast":["2","2"],"result":["2","1"],"opinion":"เลวาเดีย ทาลลินด์ บุกมาเล่นแบบชิลล์ๆ ดึงเสมอ","winner":"เซนต์ยาร์นาน"},{"league_name":"ยูฟ่า ยูโรปา ลีก (UEFA Europa League)","time":"03:00","home":"เซนต์ยาร์นาน","away":"เลวาเดีย ทาลลินน์","ratio":"0.5/1 -5","forecast":["2","2"],"result":["2","1"],"opinion":"เลวาเดีย ทาลลินด์ บุกมาเล่นแบบชิลล์ๆ ดึงเสมอ","winner":"เซนต์ยาร์นาน"},{"league_name":"ยูฟ่า ยูโรปา ลีก (UEFA Europa League)","time":"03:00","home":"เซนต์ยาร์นาน","away":"เลวาเดีย ทาลลินน์","ratio":"0.5/1 -5","forecast":["2","2"],"result":["2","1"],"opinion":"เลวาเดีย ทาลลินด์ บุกมาเล่นแบบชิลล์ๆ ดึงเสมอ","winner":"เซนต์ยาร์นาน"},{"league_name":"ยูฟ่า ยูโรปา ลีก (UEFA Europa League)","time":"03:00","home":"เซนต์ยาร์นาน","away":"เลวาเดีย ทาลลินน์","ratio":"0.5/1 -5","forecast":["2","2"],"result":["2","1"],"opinion":"เลวาเดีย ทาลลินด์ บุกมาเล่นแบบชิลล์ๆ ดึงเสมอ","winner":"เซนต์ยาร์นาน"},{"league_name":"ยูฟ่า ยูโรปา ลีก (UEFA Europa League)","time":"03:00","home":"เซนต์ยาร์นาน","away":"เลวาเดีย ทาลลินน์","ratio":"0.5/1 -5","forecast":["2","2"],"result":["2","1"],"opinion":"เลวาเดีย ทาลลินด์ บุกมาเล่นแบบชิลล์ๆ ดึงเสมอ","winner":"เซนต์ยาร์นาน"},{"league_name":"ยูฟ่า ยูโรปา ลีก (UEFA Europa League)","time":"03:00","home":"เซนต์ยาร์นาน","away":"เลวาเดีย ทาลลินน์","ratio":"0.5/1 -5","forecast":["2","2"],"result":["2","1"],"opinion":"เลวาเดีย ทาลลินด์ บุกมาเล่นแบบชิลล์ๆ ดึงเสมอ","winner":"เซนต์ยาร์นาน"},{"league_name":"ยูฟ่า ยูโรปา ลีก (UEFA Europa League)","time":"03:00","home":"เซนต์ยาร์นาน","away":"เลวาเดีย ทาลลินน์","ratio":"0.5/1 -5","forecast":["2","2"],"result":["2","1"],"opinion":"เลวาเดีย ทาลลินด์ บุกมาเล่นแบบชิลล์ๆ ดึงเสมอ","winner":"เซนต์ยาร์นาน"},{"league_name":"ยูฟ่า ยูโรปา ลีก (UEFA Europa League)","time":"03:00","home":"เซนต์ยาร์นาน","away":"เลวาเดีย ทาลลินน์","ratio":"0.5/1 -5","forecast":["2","2"],"result":["2","1"],"opinion":"เลวาเดีย ทาลลินด์ บุกมาเล่นแบบชิลล์ๆ ดึงเสมอ","winner":"เซนต์ยาร์นาน"},{"league_name":"ยูฟ่า ยูโรปา ลีก (UEFA Europa League)","time":"03:00","home":"เซนต์ยาร์นาน","away":"เลวาเดีย ทาลลินน์","ratio":"0.5/1 -5","forecast":["2","2"],"result":["2","1"],"opinion":"เลวาเดีย ทาลลินด์ บุกมาเล่นแบบชิลล์ๆ ดึงเสมอ","winner":"เซนต์ยาร์นาน"},{"league_name":"ยูฟ่า ยูโรปา ลีก (UEFA Europa League)","time":"03:00","home":"เซนต์ยาร์นาน","away":"เลวาเดีย ทาลลินน์","ratio":"0.5/1 -5","forecast":["2","2"],"result":["2","1"],"opinion":"เลวาเดีย ทาลลินด์ บุกมาเล่นแบบชิลล์ๆ ดึงเสมอ","winner":"เซนต์ยาร์นาน"},{"league_name":"ยูฟ่า ยูโรปา ลีก (UEFA Europa League)","time":"03:00","home":"เซนต์ยาร์นาน","away":"เลวาเดีย ทาลลินน์","ratio":"0.5/1 -5","forecast":["2","2"],"result":["2","1"],"opinion":"เลวาเดีย ทาลลินด์ บุกมาเล่นแบบชิลล์ๆ ดึงเสมอ","winner":"เซนต์ยาร์นาน"},{"league_name":"ยูฟ่า ยูโรปา ลีก (UEFA Europa League)","time":"03:00","home":"เซนต์ยาร์นาน","away":"เลวาเดีย ทาลลินน์","ratio":"0.5/1 -5","forecast":["2","2"],"result":["2","1"],"opinion":"เลวาเดีย ทาลลินด์ บุกมาเล่นแบบชิลล์ๆ ดึงเสมอ","winner":"เซนต์ยาร์นาน"},{"league_name":"ยูฟ่า ยูโรปา ลีก (UEFA Europa League)","time":"03:00","home":"เซนต์ยาร์นาน","away":"เลวาเดีย ทาลลินน์","ratio":"0.5/1 -5","forecast":["2","2"],"result":["2","1"],"opinion":"เลวาเดีย ทาลลินด์ บุกมาเล่นแบบชิลล์ๆ ดึงเสมอ","winner":"เซนต์ยาร์นาน"},{"league_name":"ยูฟ่า ยูโรปา ลีก (UEFA Europa League)","time":"03:00","home":"เซนต์ยาร์นาน","away":"เลวาเดีย ทาลลินน์","ratio":"0.5/1 -5","forecast":["2","2"],"result":["2","1"],"opinion":"เลวาเดีย ทาลลินด์ บุกมาเล่นแบบชิลล์ๆ ดึงเสมอ","winner":"เซนต์ยาร์นาน"},{"league_name":"ยูฟ่า ยูโรปา ลีก (UEFA Europa League)","time":"03:00","home":"เซนต์ยาร์นาน","away":"เลวาเดีย ทาลลินน์","ratio":"0.5/1 -5","forecast":["2","2"],"result":["2","1"],"opinion":"เลวาเดีย ทาลลินด์ บุกมาเล่นแบบชิลล์ๆ ดึงเสมอ","winner":"เซนต์ยาร์นาน"},{"league_name":"ยูฟ่า ยูโรปา ลีก (UEFA Europa League)","time":"03:00","home":"เซนต์ยาร์นาน","away":"เลวาเดีย ทาลลินน์","ratio":"0.5/1 -5","forecast":["2","2"],"result":["2","1"],"opinion":"เลวาเดีย ทาลลินด์ บุกมาเล่นแบบชิลล์ๆ ดึงเสมอ","winner":"เซนต์ยาร์นาน"},{"league_name":"ยูฟ่า ยูโรปา ลีก (UEFA Europa League)","time":"03:00","home":"เซนต์ยาร์นาน","away":"เลวาเดีย ทาลลินน์","ratio":"0.5/1 -5","forecast":["2","2"],"result":["2","1"],"opinion":"เลวาเดีย ทาลลินด์ บุกมาเล่นแบบชิลล์ๆ ดึงเสมอ","winner":"เซนต์ยาร์นาน"},{"league_name":"ยูฟ่า ยูโรปา ลีก (UEFA Europa League)","time":"03:00","home":"เซนต์ยาร์นาน","away":"เลวาเดีย ทาลลินน์","ratio":"0.5/1 -5","forecast":["2","2"],"result":["2","1"],"opinion":"เลวาเดีย ทาลลินด์ บุกมาเล่นแบบชิลล์ๆ ดึงเสมอ","winner":"เซนต์ยาร์นาน"},{"league_name":"ยูฟ่า ยูโรปา ลีก (UEFA Europa League)","time":"03:00","home":"เซนต์ยาร์นาน","away":"เลวาเดีย ทาลลินน์","ratio":"0.5/1 -5","forecast":["2","2"],"result":["2","1"],"opinion":"เลวาเดีย ทาลลินด์ บุกมาเล่นแบบชิลล์ๆ ดึงเสมอ","winner":"เซนต์ยาร์นาน"},{"league_name":"ยูฟ่า ยูโรปา ลีก (UEFA Europa League)","time":"03:00","home":"เซนต์ยาร์นาน","away":"เลวาเดีย ทาลลินน์","ratio":"0.5/1 -5","forecast":["2","2"],"result":["2","1"],"opinion":"เลวาเดีย ทาลลินด์ บุกมาเล่นแบบชิลล์ๆ ดึงเสมอ","winner":"เซนต์ยาร์นาน"},{"league_name":"ยูฟ่า ยูโรปา ลีก (UEFA Europa League)","time":"03:00","home":"เซนต์ยาร์นาน","away":"เลวาเดีย ทาลลินน์","ratio":"0.5/1 -5","forecast":["2","2"],"result":["2","1"],"opinion":"เลวาเดีย ทาลลินด์ บุกมาเล่นแบบชิลล์ๆ ดึงเสมอ","winner":"เซนต์ยาร์นาน"},{"league_name":"ยูฟ่า ยูโรปา ลีก (UEFA Europa League)","time":"03:00","home":"เซนต์ยาร์นาน","away":"เลวาเดีย ทาลลินน์","ratio":"0.5/1 -5","forecast":["2","2"],"result":["2","1"],"opinion":"เลวาเดีย ทาลลินด์ บุกมาเล่นแบบชิลล์ๆ ดึงเสมอ","winner":"เซนต์ยาร์นาน"},{"league_name":"แอฟริกันเนชั่นคัพ (Africa Cup of Nations)","time":"02:00","home":"ตูนีเซีย","away":"มาดากัสการ์","ratio":"0.5","forecast":["1","0"],"result":["3","0"],"opinion":"(อียิปต์) รอบลึกๆตูนีเซียน่าเชียร์กว่ามาดากัสการ์","winner":"ตูนีเซีย"},{"league_name":"แอฟริกันเนชั่นคัพ (Africa Cup of Nations)","time":"02:00","home":"ตูนีเซีย","away":"มาดากัสการ์","ratio":"0.5","forecast":["1","0"],"result":["3","0"],"opinion":"(อียิปต์) รอบลึกๆตูนีเซียน่าเชียร์กว่ามาดากัสการ์","winner":"ตูนีเซีย"},{"league_name":"บราซิล คัพ (Copa do Brasil)","time":"07:30","home":"ครูไซโร","away":"แอตเลติโก้ มิไนโร่","ratio":"0.5 -5","forecast":["2","0"],"result":["3","0"],"opinion":"ครูไซโรเกมส์เหย้าเจอใครก็ได้ งามไส้แล้วทีมเยือน","winner":"ครูไซโร"},{"league_name":"โคปา ซูดาเมริกาน่า (Copa Sudamericana de Clubes)","time":"07:30","home":"โคล่อน","away":"อาร์เจนติโนส จูเนียร์","ratio":"0/0.5 -10","forecast":["1","1"],"result":["0","1"],"opinion":"อาร์เจนติโนสฯ ไม่ใช่ทีมไก่กา คิดว่าชนะได้เหรอ","winner":""},{"league_name":"เยอรมันรีเจนนัลบาวาเรีย(Germany Regional Bavaria)","time":"00:00","home":"อิลเลอร์ทิสเซ่น","away":"FC เมมมิงเก้น","ratio":"0/0.5 -10","forecast":["2","2"],"result":["2","0"],"opinion":"บอลสามหน้าแบบนี้ แถมฟอร์มสูสีเห็นทีต้องมาเยือน","winner":"อิลเลอร์ทิสเซ่น"},{"league_name":"จีน ซูเปอร์ลีก (China Football Super League)","time":"19:00","home":"เทียนจิน เทด้า","away":"กว่างโจว เอเวอร์แกรนด์","ratio":"1/1.5 -5","forecast":["0","2"],"result":["0","3"],"opinion":"แมทต์นี้กว่างโจวฯ ชนะแน่ๆแต่ต้องนั่งลุ้นว่าขาดไม๊","winner":""}]}